{
    "IMNN": {
        "2025-06-05": {
            "result": {
                "ticker": "IMNN",
                "probability_value": 10,
                "confidence": 4,
                "justification": "Choppy, low volume, indecisive",
                "fundamental_impact": "Poor financials",
                "extra": "too risky, avoid"
            }
        },
        "2025-05-22": {
            "result": {
                "ticker": "IMNN",
                "recommendation": "Due to the significant downtrend and high volatility observed in IMNN, maintaining a cautious stance is advisable. The trend-following and momentum analysis indicate continued downward pressure. While volume spikes suggest some trading activity, the overall negative trend outweighs any potential short-term gains. Therefore, a 'Sell' recommendation is warranted to mitigate potential losses.",
                "weights": {
                    "trend_following": 0.4,
                    "momentum_analysis": 0.25,
                    "volume_spikes": 0.15,
                    "volatility_atr": 0.07,
                    "support_resistance": 0.05,
                    "breakout_detection": 0.03,
                    "liquidity_spread": 0.02,
                    "market_breadth": 0.01,
                    "correlation_index": 0.01,
                    "fundamentals": 0.01
                }
            },
            "feedback": "failure"
        }
    },
    "AAPL": {
        "2025-06-05": {
            "result": {
                "ticker": "AAPL",
                "probability_value": 20,
                "confidence": 6,
                "justification": "Downtrend, volume spike selloff",
                "fundamental_impact": "Mixed earnings.",
                "extra": "RSI oversold bounce possible"
            }
        },
        "2025-05-22": {
            "result": {
                "ticker": "AAPL",
                "recommendation": "AAPL shows a recent downturn but also demonstrates resilience with high trading volumes. Trend-following indicates a short-term downward trend, yet momentum analysis suggests potential for a rebound. Given the stock's volatility and the mixed signals from technical indicators, a 'Hold' recommendation is appropriate. Monitoring the stock's price action for signs of a sustained recovery is crucial before considering a 'Buy' strategy.",
                "weights": {
                    "trend_following": 0.4,
                    "momentum_analysis": 0.25,
                    "volume_spikes": 0.15,
                    "volatility_atr": 0.07,
                    "support_resistance": 0.05,
                    "breakout_detection": 0.03,
                    "liquidity_spread": 0.02,
                    "market_breadth": 0.01,
                    "correlation_index": 0.01,
                    "fundamentals": 0.01
                }
            },
            "feedback": "success"
        }
    }
}